README.rst
setup.py
volatile/__init__.py
volatile.egg-info/PKG-INFO
volatile.egg-info/SOURCES.txt
volatile.egg-info/dependency_links.txt
volatile.egg-info/top_level.txt