Metadata-Version: 1.1
Name: volatile
Version: 2.1.0
Summary: A small extension for the tempfile module.
Home-page: https://github.com/mbr/volatile
Author: Marc Brinkmann
Author-email: git@marcbrinkmann.de
License: MIT
Platform: UNKNOWN
Classifier: Programming Language :: Python :: 2
Classifier: Programming Language :: Python :: 3
